aritmatika/__init__.py
aritmatika/bruto_tara_netto.py
aritmatika/bunga.py
aritmatika/gaji.py
aritmatika/pajak.py
aritmatika/rabat_diskon.py
aritmatika/untung_rugi.py
aritmatika-0.0.6.dist-info/LICENSE.txt
aritmatika-0.0.6.dist-info/METADATA
aritmatika-0.0.6.dist-info/WHEEL
aritmatika-0.0.6.dist-info/top_level.txt
aritmatika-0.0.6.dist-info/RECORD
