Metadata-Version: 2.1
Name: aritmatika
Version: 0.0.6
Summary: Aritmatika adalah Paket Python untuk menyelesaikan masalah aritmatika sosial seperti untung rugi, bunga, pajak, diskon, rabat, serta bruto, netto, dan tara.
Home-page: 
Author: kelompok 6
Author-email: mahesaputrilukman28@gmail.com
License: MIT
Keywords: Aritmatika Sosial
Classifier: Development Status :: 5 - Production/Stable
Classifier: Intended Audience :: Education
Classifier: Operating System :: Microsoft :: Windows :: Windows 10
Classifier: License :: OSI Approved :: MIT License
Classifier: Programming Language :: Python :: 3
License-File: LICENSE.txt
